agent_reminiscence/__init__.py
agent_reminiscence/core.py
agent_reminiscence/agents/__init__.py
agent_reminiscence/agents/er_extractor.py
agent_reminiscence/agents/memorizer.py
agent_reminiscence/agents/memory_retriever.py
agent_reminiscence/agents/memory_updater.py
agent_reminiscence/config/__init__.py
agent_reminiscence/config/settings.py
agent_reminiscence/database/__init__.py
agent_reminiscence/database/init_databases.py
agent_reminiscence/database/models.py
agent_reminiscence/database/neo4j_manager.py
agent_reminiscence/database/postgres_manager.py
agent_reminiscence/database/repositories/__init__.py
agent_reminiscence/database/repositories/active_memory.py
agent_reminiscence/database/repositories/longterm_memory.py
agent_reminiscence/database/repositories/shortterm_memory.py
agent_reminiscence/services/__init__.py
agent_reminiscence/services/central_storage.py
agent_reminiscence/services/embedding.py
agent_reminiscence/services/llm_model_provider.py
agent_reminiscence/services/memory_manager.py
agent_reminiscence/utils/__init__.py
agent_reminiscence/utils/agent_logger.py
agent_reminiscence/utils/helpers.py
agent_reminiscence-0.1.3.dist-info/licenses/LICENSE
agent_reminiscence_mcp/__main__.py
agent_reminiscence_mcp/run.py
agent_reminiscence_mcp/schemas.py
agent_reminiscence_mcp/server.py
agent_reminiscence_mcp/test_server.py
agent_reminiscence_mcp/tests/add_sample_data.py
agent_reminiscence_mcp/tests/test_agent_mem_copilot.py
agent_reminiscence_mcp/tests/test_batch_update.py
agent_reminiscence_mcp/tests/test_mcp_client.py
agent_reminiscence-0.1.3.dist-info/METADATA
agent_reminiscence-0.1.3.dist-info/WHEEL
agent_reminiscence-0.1.3.dist-info/top_level.txt
agent_reminiscence-0.1.3.dist-info/RECORD
