Metadata-Version: 2.4
Name: agent-reminiscence
Version: 0.1.3
Summary: Hierarchical memory management for AI agents with vector search and graph relationships
Author: Agent Reminiscence Contributors
Maintainer: Agent Reminiscence Contributors
License: MIT
Project-URL: Homepage, https://github.com/Ganzzi/agent-reminiscence
Project-URL: Documentation, https://github.com/Ganzzi/agent-reminiscence/tree/main/docs
Project-URL: Repository, https://github.com/Ganzzi/agent-reminiscence
Project-URL: Issues, https://github.com/Ganzzi/agent-reminiscence/issues
Project-URL: Changelog, https://github.com/Ganzzi/agent-reminiscence/blob/main/CHANGELOG.md
Keywords: ai,memory,agents,vector-search,graph,pydantic-ai,llm,rag,knowledge-graph
Classifier: Development Status :: 3 - Alpha
Classifier: Intended Audience :: Developers
Classifier: License :: OSI Approved :: MIT License
Classifier: Programming Language :: Python :: 3
Classifier: Programming Language :: Python :: 3.10
Classifier: Programming Language :: Python :: 3.11
Classifier: Programming Language :: Python :: 3.12
Classifier: Topic :: Scientific/Engineering :: Artificial Intelligence
Classifier: Topic :: Software Development :: Libraries :: Python Modules
Classifier: Framework :: AsyncIO
Requires-Python: >=3.10
License-File: LICENSE
Requires-Dist: pydantic>=2.0.0
Requires-Dist: pydantic-ai>=0.3.4
Requires-Dist: pydantic-ai-slim[anthropic,google,openai]>=0.3.4
Requires-Dist: psqlpy>=0.11.0
Requires-Dist: neo4j>=5.16.0
Requires-Dist: requests>=2.31.0
Requires-Dist: asyncio>=3.4.3
Requires-Dist: numpy>=1.24.0
Provides-Extra: dev
Requires-Dist: pytest>=7.4.0; extra == "dev"
Requires-Dist: pytest-asyncio>=0.21.0; extra == "dev"
Requires-Dist: pytest-cov>=4.1.0; extra == "dev"
Requires-Dist: black>=23.0.0; extra == "dev"
Requires-Dist: ruff>=0.1.0; extra == "dev"
Requires-Dist: mypy>=1.5.0; extra == "dev"
Requires-Dist: python-dotenv>=1.0.0; extra == "dev"
Provides-Extra: mcp
Requires-Dist: mcp[cli]>=1.0.0; extra == "mcp"
Provides-Extra: docs
Requires-Dist: mkdocs>=1.5.0; extra == "docs"
Requires-Dist: mkdocs-material>=9.0.0; extra == "docs"
Requires-Dist: mkdocstrings[python]>=0.24.0; extra == "docs"
Dynamic: license-file
